odoo/addons/metadata/__init__.py
odoo/addons/metadata/__manifest__.py
odoo/addons/metadata/models/__init__.py
odoo/addons/metadata/models/metadata_line.py
odoo/addons/metadata/security/ir.model.access.csv
odoo_addon_metadata-16.0.1.0.0.dist-info/METADATA
odoo_addon_metadata-16.0.1.0.0.dist-info/WHEEL
odoo_addon_metadata-16.0.1.0.0.dist-info/top_level.txt
odoo_addon_metadata-16.0.1.0.0.dist-info/RECORD
