Metadata-Version: 2.1
Name: odoo-addon-metadata
Version: 16.0.1.0.0
Summary: Save custom metadata on any model
Home-page: 
Author: Coopdevs Treball SCCL
License: AGPL-3
Classifier: Programming Language :: Python
Classifier: Framework :: Odoo
Classifier: Framework :: Odoo :: 16.0
Classifier: License :: OSI Approved :: GNU Affero General Public License v3
Requires-Python: >=3.10
Requires-Dist: odoo<16.1dev,>=16.0a
